peasy_jobs/__about__.py
peasy_jobs/__init__.py
peasy_jobs/admin.py
peasy_jobs/apps.py
peasy_jobs/models.py
peasy_jobs/peasy_jobs.py
peasy_jobs/management/__init__.py
peasy_jobs/management/commands/__init__.py
peasy_jobs/management/commands/execute_job.py
peasy_jobs/management/commands/run_peasy.py
peasy_jobs/migrations/0001_initial.py
peasy_jobs/migrations/0002_peasyjobqueue_user.py
peasy_jobs/migrations/__init__.py
peasy_jobs-0.4.1.dist-info/METADATA
peasy_jobs-0.4.1.dist-info/WHEEL
peasy_jobs-0.4.1.dist-info/licenses/LICENSE.txt
peasy_jobs-0.4.1.dist-info/RECORD
