Metadata-Version: 2.3
Name: peasy-jobs
Version: 0.4.1
Summary: An incredibly simple database-based background worker for Django.
Project-URL: Documentation, https://github.com/d-flood/peasy-jobs#readme
Project-URL: Issues, https://github.com/d-flood/peasy-jobs/issues
Project-URL: Source, https://github.com/d-flood/peasy-jobs
Author-email: David Flood <69060117+d-flood@users.noreply.github.com>
License: MIT
Keywords: background,database,django,job,jobs,peasy,queue,task,worker
Classifier: Development Status :: 4 - Beta
Classifier: Programming Language :: Python
Classifier: Programming Language :: Python :: 3.11
Classifier: Programming Language :: Python :: 3.12
Classifier: Programming Language :: Python :: 3.13
Classifier: Programming Language :: Python :: Implementation :: CPython
Requires-Python: >=3.10
Requires-Dist: django>=4.2
